[{"anonymous":false,"inputs":[{"indexed":true,"internalType":"address","name":"market","type":"address"},{"indexed":true,"internalType":"address","name":"collateralToken","type":"address"},{"indexed":true,"internalType":"address","name":"loanToken","type":"address"},{"indexed":false,"internalType":"uint256","name":"ltvBps","type":"uint256"}],"name":"MarketCreated","type":"event"},{"inputs":[{"internalType":"address","name":"collateralToken","type":"address"},{"internalType":"address","name":"loanToken","type":"address"},{"internalType":"uint256","name":"ltvBps","type":"uint256"}],"name":"createMarket","outputs":[{"internalType":"address","name":"market","type":"address"}],"stateMutability":"nonpayable","type":"function"},{"inputs":[{"internalType":"uint256","name":"index","type":"uint256"}],"name":"getMarket","outputs":[{"components":[{"internalType":"address","name":"market","type":"address"},{"internalType":"address","name":"collateralToken","type":"address"},{"internalType":"address","name":"loanToken","type":"address"},{"internalType":"uint256","name":"ltvBps","type":"uint256"},{"internalType":"bool","name":"active","type":"bool"}],"internalType":"struct MarketFactory.MarketInfo","name":"","type":"tuple"}],"stateMutability":"view","type":"function"},{"inputs":[],"name":"getMarkets","outputs":[{"components":[{"internalType":"address","name":"market","type":"address"},{"internalType":"address","name":"collateralToken","type":"address"},{"internalType":"address","name":"loanToken","type":"address"},{"internalType":"uint256","name":"ltvBps","type":"uint256"},{"internalType":"bool","name":"active","type":"bool"}],"internalType":"struct MarketFactory.MarketInfo[]","name":"","type":"tuple[]"}],"stateMutability":"view","type":"function"},{"inputs":[],"name":"marketCount","outputs":[{"internalType":"uint256","name":"","type":"uint256"}],"stateMutability":"view","type":"function"}]